mantium_client/__init__.py
mantium_client/api_client.py
mantium_client/invoke_tasks/__init__.py
mantium_client/invoke_tasks/build.py
mantium_client/invoke_tasks/test.py
mantium_client/invoke_tasks/utils.py
mantium_client/version.py
mantium_client-0.1.7.dist-info/LICENSE.txt
mantium_client-0.1.7.dist-info/METADATA
mantium_client-0.1.7.dist-info/WHEEL
mantium_client-0.1.7.dist-info/RECORD
