Metadata-Version: 2.1
Name: mantium-client
Version: 0.1.7
Summary: Python client for the Mantium API
Home-page: https://github.com/mantiumai/mantium-client-py
License: Apache-2.0
Keywords: mantium,ChatGPT,AI
Author: Mantium
Author-email: support@mantiumai.com
Requires-Python: >=3.8.1,<4.0.0
Classifier: Development Status :: 4 - Beta
Classifier: Intended Audience :: Developers
Classifier: License :: OSI Approved :: Apache Software License
Classifier: Natural Language :: English
Classifier: Operating System :: OS Independent
Classifier: Programming Language :: Python
Classifier: Programming Language :: Python :: 3
Classifier: Programming Language :: Python :: 3.9
Classifier: Programming Language :: Python :: 3.10
Classifier: Programming Language :: Python :: 3.11
Classifier: Programming Language :: Python :: 3.8
Classifier: Topic :: Scientific/Engineering
Classifier: Topic :: Scientific/Engineering :: Artificial Intelligence
Classifier: Topic :: Software Development :: Libraries :: Python Modules
Classifier: Topic :: Software Development :: Pre-processors
Requires-Dist: fastapi (>=0.97.0,<0.98.0)
Requires-Dist: mantium-spec (==1.0.976)
Requires-Dist: pre-commit (==2.20.0)
Requires-Dist: pydantic (>=1.10.2,<2.0.0)
Requires-Dist: requests (>=2.31.0,<3.0.0)
Requires-Dist: tenacity (>=8.2.2,<9.0.0)
Requires-Dist: types-requests (>=2.31.0.1,<3.0.0.0)
Project-URL: Repository, https://github.com/mantiumai/mantium-client-py
